llm_fiber/__init__.py
llm_fiber/batch.py
llm_fiber/budgets.py
llm_fiber/fiber.py
llm_fiber/retry.py
llm_fiber/routing.py
llm_fiber/sync.py
llm_fiber/timeouts.py
llm_fiber/types.py
llm_fiber/caching/__init__.py
llm_fiber/caching/memory.py
llm_fiber/observability/logging.py
llm_fiber/observability/metrics.py
llm_fiber/providers/__init__.py
llm_fiber/providers/anthropic.py
llm_fiber/providers/base.py
llm_fiber/providers/gemini.py
llm_fiber/providers/openai.py
llm_fiber/py.typed
llm_fiber-1.0.1.dist-info/METADATA
llm_fiber-1.0.1.dist-info/WHEEL
llm_fiber-1.0.1.dist-info/licenses/LICENSE
llm_fiber-1.0.1.dist-info/RECORD
