Metadata-Version: 2.4
Name: llm-fiber
Version: 1.0.1
Summary: A thin, fast, observable Python client for LLMs
Project-URL: Homepage, https://github.com/aimlesx/llm-fiber
Project-URL: Documentation, https://github.com/aimlesx/llm-fiber/blob/main/docs/index.md
Project-URL: Repository, https://github.com/aimlesx/llm-fiber
Project-URL: Bug Tracker, https://github.com/aimlesx/llm-fiber/issues
Project-URL: Changelog, https://github.com/aimlesx/llm-fiber/releases
Author: Aimless
Maintainer: Aimless
License: MIT
License-File: LICENSE
Keywords: ai,anthropic,async,chat,completion,gemini,llm,openai,streaming
Classifier: Development Status :: 5 - Production/Stable
Classifier: Framework :: AsyncIO
Classifier: Intended Audience :: Developers
Classifier: License :: OSI Approved :: MIT License
Classifier: Operating System :: OS Independent
Classifier: Programming Language :: Python :: 3
Classifier: Programming Language :: Python :: 3.8
Classifier: Programming Language :: Python :: 3.9
Classifier: Programming Language :: Python :: 3.10
Classifier: Programming Language :: Python :: 3.11
Classifier: Programming Language :: Python :: 3.12
Classifier: Topic :: Scientific/Engineering :: Artificial Intelligence
Classifier: Topic :: Software Development :: Libraries :: Python Modules
Classifier: Typing :: Typed
Requires-Python: >=3.8
Requires-Dist: httpx>=0.24.0
Requires-Dist: typing-extensions>=4.0.0; python_version < '3.10'
Provides-Extra: all
Requires-Dist: opentelemetry-api>=1.15.0; extra == 'all'
Requires-Dist: opentelemetry-exporter-otlp>=1.15.0; extra == 'all'
Requires-Dist: opentelemetry-sdk>=1.15.0; extra == 'all'
Requires-Dist: statsd>=3.3.0; extra == 'all'
Requires-Dist: structlog>=22.1.0; extra == 'all'
Requires-Dist: tiktoken>=0.4.0; extra == 'all'
Provides-Extra: dev
Requires-Dist: build>=1.0.0; extra == 'dev'
Requires-Dist: hatch>=1.9.0; extra == 'dev'
Requires-Dist: mypy>=1.0.0; extra == 'dev'
Requires-Dist: pre-commit>=3.0.0; extra == 'dev'
Requires-Dist: psutil>=5.0.0; extra == 'dev'
Requires-Dist: pytest-asyncio>=0.21.0; extra == 'dev'
Requires-Dist: pytest-cov>=4.0.0; extra == 'dev'
Requires-Dist: pytest>=7.0.0; extra == 'dev'
Requires-Dist: ruff>=0.12.12; extra == 'dev'
Requires-Dist: twine>=4.0.2; extra == 'dev'
Provides-Extra: docs
Requires-Dist: furo>=2024.0.0; extra == 'docs'
Requires-Dist: myst-parser>=2.0.0; extra == 'docs'
Requires-Dist: sphinx-autobuild>=2021.3.14; extra == 'docs'
Requires-Dist: sphinx>=7.0.0; extra == 'docs'
Provides-Extra: otel
Requires-Dist: opentelemetry-api>=1.15.0; extra == 'otel'
Requires-Dist: opentelemetry-exporter-otlp>=1.15.0; extra == 'otel'
Requires-Dist: opentelemetry-sdk>=1.15.0; extra == 'otel'
Provides-Extra: statsd
Requires-Dist: statsd>=3.3.0; extra == 'statsd'
Provides-Extra: structlog
Requires-Dist: structlog>=22.1.0; extra == 'structlog'
Provides-Extra: tokens
Requires-Dist: tiktoken>=0.4.0; extra == 'tokens'
